cmdstanjupyter/__init__.py
cmdstanjupyter/_version.py
cmdstanjupyter-2.0.0.data/data/share/jupyter/labextensions/cmdstanjupyter/package.json
cmdstanjupyter-2.0.0.data/data/share/jupyter/labextensions/cmdstanjupyter/static/365.580c146aa9e62650622c.js
cmdstanjupyter-2.0.0.data/data/share/jupyter/labextensions/cmdstanjupyter/static/remoteEntry.16453ca29bfc7685e4a9.js
cmdstanjupyter-2.0.0.data/data/share/jupyter/labextensions/cmdstanjupyter/static/style.js
cmdstanjupyter-2.0.0.data/data/share/jupyter/labextensions/cmdstanjupyter/static/third-party-licenses.json
cmdstanjupyter-2.0.0.data/data/share/jupyter/labextensions/cmdstanjupyter/install.json
cmdstanjupyter-2.0.0.dist-info/METADATA
cmdstanjupyter-2.0.0.dist-info/WHEEL
cmdstanjupyter-2.0.0.dist-info/licenses/LICENSE
cmdstanjupyter-2.0.0.dist-info/RECORD
