Metadata-Version: 2.4
Name: cmdstanjupyter
Version: 2.0.0
Summary: A JupyterLab extension for Stan models.
Project-URL: Homepage, https://github.com/WardBrian/CmdStanJupyter
Project-URL: Bug Tracker, https://github.com/WardBrian/CmdStanJupyter/issues
Project-URL: Repository, https://github.com/WardBrian/CmdStanJupyter.git
Author-email: Brian Ward <bward@flatironinstitute.org>
License: MIT License
License-File: LICENSE
Keywords: jupyter,jupyterlab,jupyterlab-extension
Classifier: Framework :: Jupyter
Classifier: Framework :: Jupyter :: JupyterLab
Classifier: Framework :: Jupyter :: JupyterLab :: 4
Classifier: Framework :: Jupyter :: JupyterLab :: Extensions
Classifier: Framework :: Jupyter :: JupyterLab :: Extensions :: Prebuilt
Classifier: License :: OSI Approved :: MIT License
Classifier: Programming Language :: Python
Classifier: Programming Language :: Python :: 3
Classifier: Programming Language :: Python :: 3.9
Classifier: Programming Language :: Python :: 3.10
Classifier: Programming Language :: Python :: 3.11
Classifier: Programming Language :: Python :: 3.12
Classifier: Programming Language :: Python :: 3.13
Requires-Python: >=3.9
Requires-Dist: humanize
